fideparser/__init__.py
fideparser/arbiter.py
fideparser/exceptions.py
fideparser/jsonencdec.py
fideparser/main.py
fideparser/mergecsv.py
fideparser/ratingperiod.py
fideparser/report.py
fideparser/tournament.py
fideparser-1.1.dist-info/METADATA
fideparser-1.1.dist-info/WHEEL
fideparser-1.1.dist-info/entry_points.txt
fideparser-1.1.dist-info/top_level.txt
fideparser-1.1.dist-info/RECORD
