Metadata-Version: 2.1
Name: fideparser
Version: 1.1
Summary: A package to export tournament info from FIDE site
Home-page: https://github.com/erral/fideparser
Author: Mikel Larreategi
Author-email: larreategi@eibar.org
License: GPL
Keywords: fide rating export
Requires-Dist: beautifulsoup4
Requires-Dist: requests
Requires-Dist: unicodecsv
Provides-Extra: test
Requires-Dist: responses ; extra == 'test'
Requires-Dist: mock ; extra == 'test'
